autoleastsq
