Metadata-Version: 2.1
Name: autoleastsq
Version: 1.0.1
Summary: 自动化拟合多项式，并自动判断最佳次幂
Home-page: UNKNOWN
Author: sheerfish
Author-email: first@sheerfish.top
License: UNKNOWN
Platform: UNKNOWN
Classifier: Programming Language :: Python :: 3
Classifier: License :: OSI Approved :: MIT License
Classifier: Operating System :: OS Independent
